pib_cli/__init__.py
pib_cli/bash/bash_git
pib_cli/bash/bash_profile
pib_cli/bash/bashrc
pib_cli/bash/shim
pib_cli/cli/__init__.py
pib_cli/cli/commands/__init__.py
pib_cli/cli/commands/bases/__init__.py
pib_cli/cli/commands/bases/command.py
pib_cli/cli/commands/bases/command_config.py
pib_cli/cli/commands/bases/fixtures/__init__.py
pib_cli/cli/commands/bases/fixtures/command_harness.py
pib_cli/cli/commands/bases/fixtures/command_harness_config.py
pib_cli/cli/commands/bases/fixtures/command_harness_exceptions.py
pib_cli/cli/commands/config_show.py
pib_cli/cli/commands/config_validate.py
pib_cli/cli/commands/config_version.py
pib_cli/cli/commands/config_where.py
pib_cli/cli/commands/container_setup.py
pib_cli/cli/commands/container_validate.py
pib_cli/cli/commands/container_version.py
pib_cli/cli/commands/customized.py
pib_cli/cli/commands/version.py
pib_cli/cli/interface/__init__.py
pib_cli/cli/interface/builtins/__init__.py
pib_cli/cli/interface/builtins/config.py
pib_cli/cli/interface/builtins/container.py
pib_cli/cli/interface/custom/__init__.py
pib_cli/config/__init__.py
pib_cli/config/default_cli_config.yml
pib_cli/config/locale/__init__.py
pib_cli/config/locale/en/LC_MESSAGES/base.po
pib_cli/config/schemas/cli_base_schema_v1.0.0.json
pib_cli/config/schemas/cli_base_schema_v2.0.0.json
pib_cli/config/schemas/cli_base_schema_v2.1.0.json
pib_cli/config/schemas/cli_cmd_schema_v0.1.0.json
pib_cli/config/yaml_keys.py
pib_cli/main.py
pib_cli/support/__init__.py
pib_cli/support/container/__init__.py
pib_cli/support/container/bases/__init__.py
pib_cli/support/container/bases/container.py
pib_cli/support/container/exceptions.py
pib_cli/support/container/installer.py
pib_cli/support/iterators/__init__.py
pib_cli/support/iterators/bases/__init__.py
pib_cli/support/iterators/bases/file_copy_base.py
pib_cli/support/iterators/bases/fixtures/__init__.py
pib_cli/support/iterators/bases/fixtures/file_copy_base_harness.py
pib_cli/support/iterators/cli_custom_commands.py
pib_cli-1.2.0.dist-info/entry_points.txt
pib_cli-1.2.0.dist-info/LICENSE
pib_cli-1.2.0.dist-info/WHEEL
pib_cli-1.2.0.dist-info/METADATA
pib_cli-1.2.0.dist-info/RECORD
