Metadata-Version: 2.1
Name: pib-cli
Version: 1.2.0
Summary: Python Development CLI
Home-page: https://github.com/niall-byrne/pib_cli
License: MPL-2.0
Keywords: development cli,development docker,development environment,development testing,development tooling,development utility,pib,python-in-a-box
Author: Niall Byrne
Author-email: niall@niallbyrne.ca
Requires-Python: >=3.7.0,<3.11.0
Classifier: Development Status :: 5 - Production/Stable
Classifier: Environment :: Console
Classifier: Intended Audience :: Developers
Classifier: License :: OSI Approved
Classifier: License :: OSI Approved :: Mozilla Public License 2.0 (MPL 2.0)
Classifier: Operating System :: POSIX :: Linux
Classifier: Programming Language :: Python
Classifier: Programming Language :: Python :: 3
Classifier: Programming Language :: Python :: 3.10
Classifier: Programming Language :: Python :: 3.7
Classifier: Programming Language :: Python :: 3.8
Classifier: Programming Language :: Python :: 3.9
Classifier: Topic :: Software Development
Classifier: Topic :: Software Development :: Build Tools
Classifier: Topic :: Software Development :: Libraries
Classifier: Topic :: Software Development :: Quality Assurance
Classifier: Topic :: Software Development :: Testing
Classifier: Topic :: Utilities
Provides-Extra: docs
Provides-Extra: docstrings
Provides-Extra: pib_docs
Provides-Extra: types
Requires-Dist: GitPython (>=3.1.26,<4.0.0)
Requires-Dist: PyYAML (>=5.4.1,<7.0.0)
Requires-Dist: bandit (>=1.7.0,<2.0.0)
Requires-Dist: click (>=8.0.1,<9.0.0)
Requires-Dist: commitizen (>=2.20.0,<3.0.0)
Requires-Dist: darglint (>=1.8.1,<2.0.0); extra == "docs"
Requires-Dist: isort (>=5.10.0,<6.0.0)
Requires-Dist: jinja2 (>=2.11.3,<4.0.0)
Requires-Dist: jsonschema (>=4.4.0,<5.0.0)
Requires-Dist: mypy; extra == "types"
Requires-Dist: pre-commit (>=2.17.0,<3.0.0)
Requires-Dist: pydocstyle (>=6.1.1,<7.0.0); extra == "docstrings"
Requires-Dist: pylint (>=2.8.3,<3.0.0)
Requires-Dist: pytest (>=7.0.1,<8.0.0)
Requires-Dist: pytest-cov (>=3.0.0,<4.0.0)
Requires-Dist: pytest-pylint (>=0.18.0,<0.19.0)
Requires-Dist: safety (>=1.10.3,<2.0.0)
Requires-Dist: sphinx (>=4.4.0,<5.0.0); extra == "docs" or extra == "pib_docs"
Requires-Dist: sphinx-autopackagesummary (>=1.3,<2.0); extra == "docs" or extra == "pib_docs"
Requires-Dist: sphinx-click (>=3.1.0,<4.0.0); extra == "pib_docs"
Requires-Dist: sphinx-intl (>=2.0.1,<3.0.0); extra == "pib_docs"
Requires-Dist: sphinx-jsonschema (>=1.17.2,<2.0.0); extra == "pib_docs"
Requires-Dist: sphinx_rtd_theme (>=1.0.0,<2.0.0); extra == "docs" or extra == "pib_docs"
Requires-Dist: wheel (>=0.37.1,<0.38.0)
Requires-Dist: yamllint (>=1.26.3,<2.0.0)
Requires-Dist: yapf (>=0.32.0,<0.33.0)
Project-URL: Documentation, https://github.com/niall-byrne/pib_cli/blob/develop/README.md
Project-URL: Repository, https://github.com/niall-byrne/pib_cli
